fourier_artist/__init__.py
fourier_artist/clean_data.py
fourier_artist/draw.py
fourier_artist-1.0.0.dist-info/LICENSE
fourier_artist-1.0.0.dist-info/METADATA
fourier_artist-1.0.0.dist-info/WHEEL
fourier_artist-1.0.0.dist-info/top_level.txt
fourier_artist-1.0.0.dist-info/RECORD
