Metadata-Version: 2.1
Name: fourier-artist
Version: 1.0.0
Summary: Swarm Intelligence in Python
Home-page: https://github.com/guofei9987/fourier_artist
Author: Guo Fei
Author-email: guofei9987@foxmail.com
License: MIT
Platform: linux
Platform: windows
Platform: macos
Requires-Python: >=3.5
Requires-Dist: numpy
Requires-Dist: scipy
